valorant/__init__.py
valorant/authorization.py
valorant/cacheManager.py
valorant/competitiveUpdate.py
valorant/party.py
valorant/rank.py
valorant/session.py
valorant/utilities.py
valorant/valorant-api.py
valorant/chat/conversation.py
valorant/chat/conversations.py
valorant/chat/conversationsManager.py
valorant/chat/message.py
valorant/match/match.py
valorant/match/pregame.py
valorant/match/previousMatch.py
valorant/social/socialManager.py
valorant/social/xmlParser.py
valorant/social/updateTypes/presenceUpdate.py
valorant/store/ownedItems.py
valorant/store/storeFront.py
valorant/store/storeManager.py
valorant/store/walletBalance.py
valorant/user/friend.py
valorant/user/localAccount.py
valorant/user/player.py
valorant/user/user.py
valorant/user/users.py
valorant_wrapper-0.1.1.dist-info/LICENSE
valorant_wrapper-0.1.1.dist-info/METADATA
valorant_wrapper-0.1.1.dist-info/WHEEL
valorant_wrapper-0.1.1.dist-info/top_level.txt
valorant_wrapper-0.1.1.dist-info/RECORD
