Metadata-Version: 2.1
Name: valorant-wrapper
Version: 0.1.1
Summary: A Python wrapper which is capable of fetching information relating to Valorant utilizing local authorization
Author: Whitelisted
Project-URL: Homepage, https://github.com/Whitelisted1/Valorant-Python-Wrapper
Project-URL: Issues, https://github.com/Whitelisted1/Valorant-Python-Wrapper/issues
Classifier: Programming Language :: Python :: 3
Classifier: License :: OSI Approved :: GNU Affero General Public License v3
Classifier: Operating System :: OS Independent
Requires-Python: >=3.8
License-File: LICENSE
Requires-Dist: requests >=2.25.1
